merci/__init__.py
merci/_version.py
merci/evaluate.py
merci/exceptions.py
merci/measures.py
merci/types.py
pipeline/__init__.py
pipeline/config.py
pipeline/datasets.py
pipeline/entrypoint.py
pipeline/experiment.py
pipeline/models.py
pipeline/options.py
merci-0.2.0.dist-info/LICENSE
merci-0.2.0.dist-info/METADATA
merci-0.2.0.dist-info/WHEEL
merci-0.2.0.dist-info/top_level.txt
merci-0.2.0.dist-info/RECORD
