Metadata-Version: 2.1
Name: merci
Version: 0.2.0
Summary: MERCI: Model Evaluation of Reliability for Classifier Inference - python package for reliability analysis of classifiers
License: MIT License
Project-URL: Homepage, https://github.com/Tremirre/merci
Requires-Python: >=3.10
License-File: LICENSE
